geobox/__init__.py
geobox/api.py
geobox/apikey.py
geobox/attachment.py
geobox/base.py
geobox/basemap.py
geobox/dashboard.py
geobox/enums.py
geobox/exception.py
geobox/feature.py
geobox/field.py
geobox/file.py
geobox/layout.py
geobox/log.py
geobox/map.py
geobox/model3d.py
geobox/mosaic.py
geobox/plan.py
geobox/query.py
geobox/raster.py
geobox/raster_analysis.py
geobox/route.py
geobox/scene.py
geobox/settings.py
geobox/table.py
geobox/task.py
geobox/tile3d.py
geobox/tileset.py
geobox/usage.py
geobox/user.py
geobox/utils.py
geobox/vector_tool.py
geobox/vectorlayer.py
geobox/version.py
geobox/view.py
geobox/workflow.py
geobox/aio/__init__.py
geobox/aio/api.py
geobox/aio/apikey.py
geobox/aio/attachment.py
geobox/aio/base.py
geobox/aio/basemap.py
geobox/aio/dashboard.py
geobox/aio/feature.py
geobox/aio/field.py
geobox/aio/file.py
geobox/aio/layout.py
geobox/aio/log.py
geobox/aio/map.py
geobox/aio/model3d.py
geobox/aio/mosaic.py
geobox/aio/plan.py
geobox/aio/query.py
geobox/aio/raster.py
geobox/aio/raster_analysis.py
geobox/aio/route.py
geobox/aio/scene.py
geobox/aio/settings.py
geobox/aio/table.py
geobox/aio/task.py
geobox/aio/tile3d.py
geobox/aio/tileset.py
geobox/aio/usage.py
geobox/aio/user.py
geobox/aio/vector_tool.py
geobox/aio/vectorlayer.py
geobox/aio/version.py
geobox/aio/view.py
geobox/aio/workflow.py
geobox-2.3.0.dist-info/licenses/LICENSE
geobox-2.3.0.dist-info/METADATA
geobox-2.3.0.dist-info/WHEEL
geobox-2.3.0.dist-info/top_level.txt
geobox-2.3.0.dist-info/RECORD
