Metadata-Version: 2.4
Name: geobox
Version: 2.3.0
Summary: Python SDK for Geobox's APIs
Author-email: Hamid Heydari <heydari.h62@gmail.com>
License: MIT
Project-URL: Homepage, https://geobox.ir
Project-URL: Documentation, https://en.geobox.ir/developers/docs-category/geobox-api-for-python/
Requires-Python: >=3.7
License-File: LICENSE
Requires-Dist: requests
Requires-Dist: python-dotenv
Provides-Extra: geometry
Requires-Dist: shapely; extra == "geometry"
Requires-Dist: pyproj; extra == "geometry"
Provides-Extra: tqdm
Requires-Dist: tqdm; extra == "tqdm"
Requires-Dist: ipywidgets; extra == "tqdm"
Provides-Extra: async
Requires-Dist: aiohttp; extra == "async"
Provides-Extra: all
Requires-Dist: shapely; extra == "all"
Requires-Dist: pyproj; extra == "all"
Requires-Dist: tqdm; extra == "all"
Requires-Dist: ipywidgets; extra == "all"
Requires-Dist: aiohttp; extra == "all"
Dynamic: license-file
